pyfilters/__init__.py
pyfilters/abc.py
pyfilters/hashmap.py
pyfilters/memory_storage.py
pyfilters/py.typed
pyfilters/redis_storage.py
pyfilters/utils.py
pyfilters/asyncio/__init__.py
pyfilters/asyncio/redis_storage.py
pyfilters-0.1.5.dist-info/METADATA
pyfilters-0.1.5.dist-info/WHEEL
pyfilters-0.1.5.dist-info/top_level.txt
pyfilters-0.1.5.dist-info/RECORD
