Metadata-Version: 2.1
Name: pyfilters
Version: 0.1.5
Summary: Bloom filters and other filter algorithms based on memory and redis
Home-page: https://github.com/synodriver/pyfilters
Author: synodriver
Author-email: diguohuangjiajinweijun@gmail.com
Maintainer: v-vinson
License: GPLv3
Project-URL: Bug Tracker, https://github.com/synodriver/pyfilters/issues
Keywords: bloomfilter
Classifier: Development Status :: 4 - Beta
Classifier: Operating System :: OS Independent
Classifier: License :: OSI Approved :: GNU General Public License v3 (GPLv3)
Classifier: Programming Language :: Python
Classifier: Programming Language :: Python :: 3.8
Classifier: Programming Language :: Python :: 3.9
Classifier: Programming Language :: Python :: 3.10
Classifier: Programming Language :: Python :: 3.11
Classifier: Programming Language :: Python :: 3.12
Classifier: Programming Language :: Python :: Implementation :: CPython
Requires-Python: >=3.7
Requires-Dist: bitarray
Requires-Dist: mmh3
Requires-Dist: typing-extensions
